ezirion_api/__init__.py
ezirion_api/courses.py
ezirion_api/utils.py
ezirion_api-0.1.2.dist-info/METADATA
ezirion_api-0.1.2.dist-info/WHEEL
ezirion_api-0.1.2.dist-info/top_level.txt
ezirion_api-0.1.2.dist-info/RECORD
