Metadata-Version: 2.1
Name: ezirion_api
Version: 0.1.2
Summary: Biblioteca de mis cursos (Prueba para mi primera api)
Home-page: https://miurlinventada.com
Author: Adrián García
